gh_release_devpi/__init__.py
gh_release_devpi/main.py
gh_release_devpi-0.1.4.dist-info/METADATA
gh_release_devpi-0.1.4.dist-info/WHEEL
gh_release_devpi-0.1.4.dist-info/entry_points.txt
gh_release_devpi-0.1.4.dist-info/licenses/LICENSE
gh_release_devpi-0.1.4.dist-info/RECORD
