Metadata-Version: 2.4
Name: gh-release-devpi
Version: 0.1.4
Summary: GitHub Release Artifact Downloader and DevPI Uploader
License-File: LICENSE
Requires-Python: >=3.11
Requires-Dist: pygithub>=2.1.1
Requires-Dist: python-dotenv>=1.0.0
Requires-Dist: requests>=2.31.0
Requires-Dist: rich>=13.0.0
Requires-Dist: tqdm>=4.66.0
Requires-Dist: typer>=0.9.0
